.gitignore
DEVELOPMENT.md
LICENSE
README.md
pyproject.toml
board2pdf.egg-info/PKG-INFO
board2pdf.egg-info/SOURCES.txt
board2pdf.egg-info/dependency_links.txt
board2pdf.egg-info/entry_points.txt
board2pdf.egg-info/requires.txt
board2pdf.egg-info/top_level.txt
plugin/install_and_launch.py
plugin/tests.py
plugin/pcm/build.py
plugin/pcm/metadata_template.json
plugin/pcm/resources/icon-64x64.png
plugin/pcm/resources/icon.png
plugin/src/__init__.py
plugin/src/_version.py
plugin/src/board2pdf_action.py
plugin/src/settings_dialog.fbp
plugin/src/dialog/__init__.py
plugin/src/dialog/dialog_base.py
plugin/src/dialog/settings_dialog.py
resources/armory-Assembly.pdf
resources/hackrf-one-Assembly.pdf
resources/screenshot.png
src/board2pdf/__init__.py
src/board2pdf/_version.py
src/board2pdf/cli.py
src/board2pdf/default_config.ini
src/board2pdf/persistence.py
src/board2pdf/plot.py
src/board2pdf/pypdf/__init__.py
src/board2pdf/pypdf/_cmap.py
src/board2pdf/pypdf/_doc_common.py
src/board2pdf/pypdf/_encryption.py
src/board2pdf/pypdf/_merger.py
src/board2pdf/pypdf/_page.py
src/board2pdf/pypdf/_page_labels.py
src/board2pdf/pypdf/_protocols.py
src/board2pdf/pypdf/_reader.py
src/board2pdf/pypdf/_utils.py
src/board2pdf/pypdf/_version.py
src/board2pdf/pypdf/_writer.py
src/board2pdf/pypdf/_xobj_image_helpers.py
src/board2pdf/pypdf/constants.py
src/board2pdf/pypdf/errors.py
src/board2pdf/pypdf/filters.py
src/board2pdf/pypdf/pagerange.py
src/board2pdf/pypdf/papersizes.py
src/board2pdf/pypdf/py.typed
src/board2pdf/pypdf/types.py
src/board2pdf/pypdf/xmp.py
src/board2pdf/pypdf/_codecs/__init__.py
src/board2pdf/pypdf/_codecs/_codecs.py
src/board2pdf/pypdf/_codecs/adobe_glyphs.py
src/board2pdf/pypdf/_codecs/pdfdoc.py
src/board2pdf/pypdf/_codecs/std.py
src/board2pdf/pypdf/_codecs/symbol.py
src/board2pdf/pypdf/_codecs/zapfding.py
src/board2pdf/pypdf/_crypt_providers/__init__.py
src/board2pdf/pypdf/_crypt_providers/_base.py
src/board2pdf/pypdf/_crypt_providers/_cryptography.py
src/board2pdf/pypdf/_crypt_providers/_fallback.py
src/board2pdf/pypdf/_crypt_providers/_pycryptodome.py
src/board2pdf/pypdf/_text_extraction/__init__.py
src/board2pdf/pypdf/_text_extraction/_layout_mode/__init__.py
