Metadata-Version: 2.2
Name: board2pdf
Version: 1.9.1
Summary: KiCAD Gerber PDF Generator
Author: Albin Dennevi
License: GNU GPLv3
Project-URL: repository, https://gitlab.com/dennevi/Board2Pdf
Project-URL: url, https://gitlab.com/dennevi/Board2Pdf
Keywords: kicad,pdf,pcb,electronics
Classifier: Programming Language :: Python :: 3
Requires-Python: >=3.6
License-File: LICENSE
Requires-Dist: pymupdf
